setup.py
srm_help/srm_help.py
srm_help.egg-info/PKG-INFO
srm_help.egg-info/SOURCES.txt
srm_help.egg-info/dependency_links.txt
srm_help.egg-info/top_level.txt