Metadata-Version: 2.1
Name: srm-help
Version: 2.6
Summary: 面向SRM团队的辅助模块，本模块内存在了部分常用的操作或者计算方法,希望能为提升数据处理效率上有所增益.
Home-page: UNKNOWN
Author: flhsjjk
Author-email: flhsjjk@mail.ustc.edu.cn
License: UNKNOWN
Platform: UNKNOWN
Classifier: Programming Language :: Python :: 3.8
Classifier: License :: OSI Approved :: MIT License
Classifier: Operating System :: OS Independent
